{
    "AdditionalData": 0,
    "Adjective": 0,
    "AetherialReduce": 0,
    "AlwaysCollectable": 0,
    "Article": 0,
    "BaseParam0": null,
    "BaseParam0Target": "BaseParam",
    "BaseParam0TargetID": 0,
    "BaseParam1": null,
    "BaseParam1Target": "BaseParam",
    "BaseParam1TargetID": 0,
    "BaseParam2": null,
    "BaseParam2Target": "BaseParam",
    "BaseParam2TargetID": 0,
    "BaseParam3": null,
    "BaseParam3Target": "BaseParam",
    "BaseParam3TargetID": 0,
    "BaseParam4": null,
    "BaseParam4Target": "BaseParam",
    "BaseParam4TargetID": 0,
    "BaseParam5": null,
    "BaseParam5Target": "BaseParam",
    "BaseParam5TargetID": 0,
    "BaseParamModifier": 0,
    "BaseParamSpecial0": null,
    "BaseParamSpecial0Target": "BaseParam",
    "BaseParamSpecial0TargetID": 0,
    "BaseParamSpecial1": null,
    "BaseParamSpecial1Target": "BaseParam",
    "BaseParamSpecial1TargetID": 0,
    "BaseParamSpecial2": null,
    "BaseParamSpecial2Target": "BaseParam",
    "BaseParamSpecial2TargetID": 0,
    "BaseParamSpecial3": null,
    "BaseParamSpecial3Target": "BaseParam",
    "BaseParamSpecial3TargetID": 0,
    "BaseParamSpecial4": null,
    "BaseParamSpecial4Target": "BaseParam",
    "BaseParamSpecial4TargetID": 0,
    "BaseParamSpecial5": null,
    "BaseParamSpecial5Target": "BaseParam",
    "BaseParamSpecial5TargetID": 0,
    "BaseParamValue0": 0,
    "BaseParamValue1": 0,
    "BaseParamValue2": 0,
    "BaseParamValue3": 0,
    "BaseParamValue4": 0,
    "BaseParamValue5": 0,
    "BaseParamValueSpecial0": 0,
    "BaseParamValueSpecial1": 0,
    "BaseParamValueSpecial2": 0,
    "BaseParamValueSpecial3": 0,
    "BaseParamValueSpecial4": 0,
    "BaseParamValueSpecial5": 0,
    "Block": 0,
    "BlockRate": 0,
    "CanBeHq": 0,
    "CastTimeS": 2,
    "ClassJobCategory": null,
    "ClassJobCategoryTarget": "ClassJobCategory",
    "ClassJobCategoryTargetID": 0,
    "ClassJobRepair": null,
    "ClassJobRepairTarget": "ClassJob",
    "ClassJobRepairTargetID": 0,
    "ClassJobUse": null,
    "ClassJobUseTarget": "ClassJob",
    "ClassJobUseTargetID": 0,
    "CooldownS": 0,
    "DamageMag": 0,
    "DamagePhys": 0,
    "DefenseMag": 0,
    "DefensePhys": 0,
    "DelayMs": 0,
    "Description": "A tiny seed rich in aromatic oil, sesame is native to Meracydia, and thought to have first been brought to Eorzea by migrating Miqo'te.",
    "DescriptionJSON": [
        "A tiny seed rich in aromatic oil, sesame is native to Meracydia, and thought to have first been brought to Eorzea by migrating Miqo'te."
    ],
    "DescriptionJSON_cn": null,
    "DescriptionJSON_de": [
        "Diese einj\u00e4hrige Pflanze stammt aus Meracydia. Die Samen werden als Zutat selbst in verschiedenen Gerichten verarbeitet oder zu einem \u00d6l gepresst."
    ],
    "DescriptionJSON_en": [
        "A tiny seed rich in aromatic oil, sesame is native to Meracydia, and thought to have first been brought to Eorzea by migrating Miqo'te."
    ],
    "DescriptionJSON_fr": [
        "Une plante annuelle de M\u00e9racydia dont on utilise les graines en cuisine, soit torr\u00e9fi\u00e9es pour leur douce saveur, soit sous forme d'huile parfum\u00e9e."
    ],
    "DescriptionJSON_ja": [
        "\u30e1\u30e9\u30b7\u30c7\u30a3\u30a2\u539f\u7523\u306e\u4e00\u5e74\u8349\u3002\u7a2e\u5b50\u3092\u98df\u6750\u3084\u9999\u6cb9\u306b\u7528\u3044\u308b"
    ],
    "DescriptionJSON_kr": null,
    "Description_cn": null,
    "Description_de": "Diese einj\u00e4hrige Pflanze stammt aus Meracydia. Die Samen werden als Zutat selbst in verschiedenen Gerichten verarbeitet oder zu einem \u00d6l gepresst.",
    "Description_en": "A tiny seed rich in aromatic oil, sesame is native to Meracydia, and thought to have first been brought to Eorzea by migrating Miqo'te.",
    "Description_fr": "Une plante annuelle de M\u00e9racydia dont on utilise les graines en cuisine, soit torr\u00e9fi\u00e9es pour leur douce saveur, soit sous forme d'huile parfum\u00e9e.",
    "Description_ja": "\u30e1\u30e9\u30b7\u30c7\u30a3\u30a2\u539f\u7523\u306e\u4e00\u5e74\u8349\u3002\u7a2e\u5b50\u3092\u98df\u6750\u3084\u9999\u6cb9\u306b\u7528\u3044\u308b",
    "Description_kr": null,
    "Desynth": 0,
    "DyeCount": 0,
    "EquipRestriction": 0,
    "EquipSlotCategory": null,
    "EquipSlotCategoryTarget": "EquipSlotCategory",
    "EquipSlotCategoryTargetID": 0,
    "FilterGroup": 12,
    "GameContentLinks": {
        "GCSupplyDuty": {
            "Item09": [
                57
            ]
        },
        "GatheringItem": {
            "Item": [
                355
            ]
        },
        "Recipe": {
            "ItemIngredient0": [
                2799
            ],
            "ItemIngredient2": [
                2855
            ],
            "ItemIngredient5": [
                2803
            ]
        },
        "RetainerTaskNormal": {
            "Item": [
                399
            ]
        }
    },
    "GamePatch": {
        "Banner": "https://img.finalfantasyxiv.com/lds/h/O/U5TufT2QVnzXONyLf61X468dFU.png",
        "ExName": "Heavensward",
        "ExVersion": 1,
        "ID": 19,
        "Name": "Patch 3.0: Heavensward",
        "Name_cn": "Patch 3.0: Heavensward",
        "Name_de": "Patch 3.0: Heavensward",
        "Name_en": "Patch 3.0: Heavensward",
        "Name_fr": "Patch 3.0: Heavensward",
        "Name_ja": "Patch 3.0: Heavensward",
        "Name_kr": "Patch 3.0: Heavensward",
        "PatchNotes": "https://na.finalfantasyxiv.com/lodestone/topics/detail/464263b3ce6026cdf98a49bf8f98c204c6199e5a",
        "PatchNotes_de": "https://de.finalfantasyxiv.com/lodestone/topics/detail/f0575b82a639492e5a70e34d823d77bddcb7f686",
        "PatchNotes_en": "https://na.finalfantasyxiv.com/lodestone/topics/detail/464263b3ce6026cdf98a49bf8f98c204c6199e5a",
        "PatchNotes_fr": "https://fr.finalfantasyxiv.com/lodestone/topics/detail/ec7affcdb9614e69cb8903810c1f9741c00bc55d",
        "PatchNotes_ja": "https://jp.finalfantasyxiv.com/lodestone/topics/detail/3a31eca82d4316c5a2fd0f68c89befb5e5791022",
        "ReleaseDate": 1434682800,
        "Version": "3.0"
    },
    "GrandCompany": null,
    "GrandCompanyTarget": "GrandCompany",
    "GrandCompanyTargetID": 0,
    "ID": 12887,
    "Icon": "/i/025000/025033.png",
    "IconHD": "/i/025000/025033_hr1.png",
    "IconID": 25033,
    "IsAdvancedMeldingPermitted": 0,
    "IsCollectable": 0,
    "IsCrestWorthy": 0,
    "IsGlamourous": 0,
    "IsIndisposable": 0,
    "IsPvP": 0,
    "IsUnique": 0,
    "IsUntradable": 0,
    "ItemAction": null,
    "ItemActionTarget": "ItemAction",
    "ItemActionTargetID": 0,
    "ItemGlamour": null,
    "ItemGlamourTarget": "Item",
    "ItemGlamourTargetID": 0,
    "ItemKind": {
        "ID": 5,
        "Name": "Medicines & Meals",
        "Name_cn": "",
        "Name_de": "Arznei/Gerichte",
        "Name_en": "Medicines & Meals",
        "Name_fr": "Consommables",
        "Name_ja": "\u85ac\u54c1\u30fb\u8abf\u7406\u54c1",
        "Name_kr": ""
    },
    "ItemRepair": null,
    "ItemRepairTarget": "ItemRepairResource",
    "ItemRepairTargetID": 0,
    "ItemSearchCategory": {
        "Category": 3,
        "ClassJob": null,
        "ClassJobTarget": "ClassJob",
        "ClassJobTargetID": 0,
        "ID": 44,
        "Icon": "/i/060000/060137.png",
        "IconHD": "/i/060000/060137_hr1.png",
        "IconID": 60137,
        "Name": "Ingredients",
        "Name_de": "Zutat",
        "Name_en": "Ingredients",
        "Name_fr": "Ingr\u00e9dient",
        "Name_ja": "\u98df\u6750",
        "Order": 1
    },
    "ItemSearchCategoryTarget": "ItemSearchCategory",
    "ItemSearchCategoryTargetID": 44,
    "ItemSeries": null,
    "ItemSeriesTarget": "ItemSeries",
    "ItemSeriesTargetID": 0,
    "ItemSortCategory": {
        "ID": 16,
        "Param": 40
    },
    "ItemSortCategoryTarget": "ItemSortCategory",
    "ItemSortCategoryTargetID": 16,
    "ItemSpecialBonus": null,
    "ItemSpecialBonusParam": 0,
    "ItemSpecialBonusTarget": "ItemSpecialBonus",
    "ItemSpecialBonusTargetID": 0,
    "ItemUICategory": {
        "ID": 45,
        "Icon": "/i/060000/060137.png",
        "IconHD": "/i/060000/060137_hr1.png",
        "IconID": 60137,
        "Name": "Ingredient",
        "Name_de": "Zutat",
        "Name_en": "Ingredient",
        "Name_fr": "Ingr\u00e9dient",
        "Name_ja": "\u98df\u6750",
        "OrderMajor": 6,
        "OrderMinor": 0
    },
    "ItemUICategoryTarget": "ItemUICategory",
    "ItemUICategoryTargetID": 45,
    "LevelEquip": 1,
    "LevelItem": 142,
    "Lot": 0,
    "Materia": null,
    "MateriaSlotCount": 0,
    "MaterializeType": 0,
    "ModelMain": "0, 0, 0, 0",
    "ModelSub": "0, 0, 0, 0",
    "Name": "Sesame Seeds",
    "Name_de": "Sesam",
    "Name_en": "Sesame Seeds",
    "Name_fr": "S\u00e9same",
    "Name_ja": "\u30bb\u30b5\u30df",
    "Patch": 19,
    "Plural": "pinches of sesame seeds",
    "Plural_de": "Handvoll[p] Sesam",
    "Plural_en": "pinches of sesame seeds",
    "Plural_fr": "brins de s\u00e9same",
    "Plural_ja": "",
    "PossessivePronoun": 0,
    "PriceLow": 2,
    "PriceMid": 674,
    "Pronoun": 0,
    "Rarity": 1,
    "RequiredPvpRank": 0,
    "Singular": "pinch of sesame seeds",
    "Singular_de": "Handvoll[p] Sesam",
    "Singular_en": "pinch of sesame seeds",
    "Singular_fr": "brin de s\u00e9same",
    "Singular_ja": "\u30bb\u30b5\u30df",
    "StackSize": 999,
    "StartsWithVowel": 0,
    "SubStatCategory": 0,
    "Url": "/Item/12887"
}