{
    "AdditionalData": 0,
    "Adjective": 0,
    "AetherialReduce": 0,
    "AlwaysCollectable": 0,
    "Article": 0,
    "BaseParam0": null,
    "BaseParam0Target": "BaseParam",
    "BaseParam0TargetID": 0,
    "BaseParam1": null,
    "BaseParam1Target": "BaseParam",
    "BaseParam1TargetID": 0,
    "BaseParam2": null,
    "BaseParam2Target": "BaseParam",
    "BaseParam2TargetID": 0,
    "BaseParam3": null,
    "BaseParam3Target": "BaseParam",
    "BaseParam3TargetID": 0,
    "BaseParam4": null,
    "BaseParam4Target": "BaseParam",
    "BaseParam4TargetID": 0,
    "BaseParam5": null,
    "BaseParam5Target": "BaseParam",
    "BaseParam5TargetID": 0,
    "BaseParamModifier": 0,
    "BaseParamSpecial0": null,
    "BaseParamSpecial0Target": "BaseParam",
    "BaseParamSpecial0TargetID": 0,
    "BaseParamSpecial1": null,
    "BaseParamSpecial1Target": "BaseParam",
    "BaseParamSpecial1TargetID": 0,
    "BaseParamSpecial2": null,
    "BaseParamSpecial2Target": "BaseParam",
    "BaseParamSpecial2TargetID": 0,
    "BaseParamSpecial3": null,
    "BaseParamSpecial3Target": "BaseParam",
    "BaseParamSpecial3TargetID": 0,
    "BaseParamSpecial4": null,
    "BaseParamSpecial4Target": "BaseParam",
    "BaseParamSpecial4TargetID": 0,
    "BaseParamSpecial5": null,
    "BaseParamSpecial5Target": "BaseParam",
    "BaseParamSpecial5TargetID": 0,
    "BaseParamValue0": 0,
    "BaseParamValue1": 0,
    "BaseParamValue2": 0,
    "BaseParamValue3": 0,
    "BaseParamValue4": 0,
    "BaseParamValue5": 0,
    "BaseParamValueSpecial0": 0,
    "BaseParamValueSpecial1": 0,
    "BaseParamValueSpecial2": 0,
    "BaseParamValueSpecial3": 0,
    "BaseParamValueSpecial4": 0,
    "BaseParamValueSpecial5": 0,
    "Block": 0,
    "BlockRate": 0,
    "CanBeHq": 1,
    "CastTimeS": 2,
    "ClassJobCategory": null,
    "ClassJobCategoryTarget": "ClassJobCategory",
    "ClassJobCategoryTargetID": 0,
    "ClassJobRepair": null,
    "ClassJobRepairTarget": "ClassJob",
    "ClassJobRepairTargetID": 0,
    "ClassJobUse": null,
    "ClassJobUseTarget": "ClassJob",
    "ClassJobUseTargetID": 0,
    "CooldownS": 0,
    "DamageMag": 0,
    "DamagePhys": 0,
    "DefenseMag": 0,
    "DefensePhys": 0,
    "DelayMs": 0,
    "Description": "A hard stone for sharpening tools made of metal or...less hard stone.",
    "DescriptionJSON": [
        "A hard stone for sharpening tools made of metal or...less hard stone."
    ],
    "DescriptionJSON_cn": null,
    "DescriptionJSON_de": [
        "Nicht besonders au\u00dfergew\u00f6hnlich, aber daf\u00fcr umso zuverl\u00e4ssiger."
    ],
    "DescriptionJSON_en": [
        "A hard stone for sharpening tools made of metal or...less hard stone."
    ],
    "DescriptionJSON_fr": [
        "Cette pierre en mudstone solide peut \u00eatre utilis\u00e9e pour aiguiser aussi bien les m\u00e9taux que les minerais."
    ],
    "DescriptionJSON_ja": [
        "\u91d1\u5c5e\u3084\u77f3\u6750\u306a\u3069\u306e\u7814\u78e8\u7528\u786c\u6ce5\u5ca9"
    ],
    "DescriptionJSON_kr": null,
    "Description_cn": null,
    "Description_de": "Nicht besonders au\u00dfergew\u00f6hnlich, aber daf\u00fcr umso zuverl\u00e4ssiger.",
    "Description_en": "A hard stone for sharpening tools made of metal or...less hard stone.",
    "Description_fr": "Cette pierre en mudstone solide peut \u00eatre utilis\u00e9e pour aiguiser aussi bien les m\u00e9taux que les minerais.",
    "Description_ja": "\u91d1\u5c5e\u3084\u77f3\u6750\u306a\u3069\u306e\u7814\u78e8\u7528\u786c\u6ce5\u5ca9",
    "Description_kr": null,
    "Desynth": 0,
    "DyeCount": 0,
    "EquipRestriction": 0,
    "EquipSlotCategory": null,
    "EquipSlotCategoryTarget": "EquipSlotCategory",
    "EquipSlotCategoryTargetID": 0,
    "FilterGroup": 12,
    "GameContentLinks": {
        "CraftLeve": {
            "Item0": [
                918535
            ]
        },
        "Recipe": {
            "ItemIngredient1": [
                3832,
                3833,
                3834,
                4562,
                4564
            ],
            "ItemIngredient2": [
                4327,
                4331,
                4333,
                4348,
                4352,
                4354,
                34074
            ],
            "ItemIngredient3": [
                3926,
                4006,
                4317,
                4318,
                4338,
                4339,
                5337,
                5338,
                5339,
                5340,
                5341,
                5342
            ],
            "ItemIngredient4": [
                3929,
                4009,
                4086,
                4089
            ],
            "ItemResult": [
                3838
            ]
        }
    },
    "GamePatch": {
        "Banner": "https://img.finalfantasyxiv.com/lds/promo/h/M/jmK4Q5CcFnBD1FfV90aw1zeUG8.png",
        "ExName": "Shadowbringers",
        "ExVersion": 3,
        "ID": 58,
        "IsExpansion": true,
        "Name": "Patch 5.0: ShadowBringers",
        "Name_cn": "Patch 5.0: ShadowBringers",
        "Name_de": "Patch 5.0: ShadowBringers",
        "Name_en": "Patch 5.0: ShadowBringers",
        "Name_fr": "Patch 5.0: ShadowBringers",
        "Name_ja": "Patch 5.0: ShadowBringers",
        "Name_kr": "Patch 5.0: ShadowBringers",
        "PatchNotes": "",
        "PatchNotes_de": "",
        "PatchNotes_en": "",
        "PatchNotes_fr": "",
        "PatchNotes_ja": "",
        "ReleaseDate": 1561712400,
        "Url": "/patch+5.0",
        "Version": "5.0"
    },
    "GrandCompany": null,
    "GrandCompanyTarget": "GrandCompany",
    "GrandCompanyTargetID": 0,
    "ID": 27802,
    "Icon": "/i/021000/021470.png",
    "IconHD": "/i/021000/021470_hr1.png",
    "IconID": 21470,
    "IsAdvancedMeldingPermitted": 0,
    "IsCollectable": 0,
    "IsCrestWorthy": 0,
    "IsGlamourous": 0,
    "IsIndisposable": 0,
    "IsPvP": 0,
    "IsUnique": 0,
    "IsUntradable": 0,
    "ItemAction": null,
    "ItemActionTarget": "ItemAction",
    "ItemActionTargetID": 0,
    "ItemGlamour": null,
    "ItemGlamourTarget": "Item",
    "ItemGlamourTargetID": 0,
    "ItemKind": {
        "ID": 6,
        "Name": "Materials",
        "Name_cn": "",
        "Name_de": "Materialien",
        "Name_en": "Materials",
        "Name_fr": "Mat\u00e9riaux",
        "Name_ja": "\u7d20\u6750",
        "Name_kr": ""
    },
    "ItemRepair": null,
    "ItemRepairTarget": "ItemRepairResource",
    "ItemRepairTargetID": 0,
    "ItemSearchCategory": {
        "Category": 3,
        "ClassJob": null,
        "ClassJobTarget": "ClassJob",
        "ClassJobTargetID": 0,
        "ID": 47,
        "Icon": "/i/060000/060139.png",
        "IconHD": "/i/060000/060139_hr1.png",
        "IconID": 60139,
        "Name": "Stone",
        "Name_de": "Baustein",
        "Name_en": "Stone",
        "Name_fr": "Pierre",
        "Name_ja": "\u77f3\u6750",
        "Order": 4
    },
    "ItemSearchCategoryTarget": "ItemSearchCategory",
    "ItemSearchCategoryTargetID": 47,
    "ItemSeries": null,
    "ItemSeriesTarget": "ItemSeries",
    "ItemSeriesTargetID": 0,
    "ItemSortCategory": {
        "ID": 16,
        "Param": 40
    },
    "ItemSortCategoryTarget": "ItemSortCategory",
    "ItemSortCategoryTargetID": 16,
    "ItemSpecialBonus": null,
    "ItemSpecialBonusParam": 0,
    "ItemSpecialBonusTarget": "ItemSpecialBonus",
    "ItemSpecialBonusTargetID": 0,
    "ItemUICategory": {
        "ID": 48,
        "Icon": "/i/060000/060139.png",
        "IconHD": "/i/060000/060139_hr1.png",
        "IconID": 60139,
        "Name": "Stone",
        "Name_de": "Baustein",
        "Name_en": "Stone",
        "Name_fr": "Pierre",
        "Name_ja": "\u77f3\u6750",
        "OrderMajor": 6,
        "OrderMinor": 2
    },
    "ItemUICategoryTarget": "ItemUICategory",
    "ItemUICategoryTargetID": 48,
    "LevelEquip": 1,
    "LevelItem": 390,
    "Lot": 0,
    "Materia": null,
    "MateriaSlotCount": 0,
    "MaterializeType": 0,
    "ModelMain": "0, 0, 0, 0",
    "ModelSub": "0, 0, 0, 0",
    "Name": "Hard Mudstone Whetstone",
    "Name_de": "Mergelwetzstein",
    "Name_en": "Hard Mudstone Whetstone",
    "Name_fr": "Pierre \u00e0 aiguiser en mudstone solide",
    "Name_ja": "\u786c\u6ce5\u5ca9\u7825\u77f3",
    "Patch": 58,
    "Plural": "hard mudstone whetstones",
    "Plural_de": "Mergelwetzsteine",
    "Plural_en": "hard mudstone whetstones",
    "Plural_fr": "pierres \u00e0 aiguiser en mudstone solide",
    "Plural_ja": "",
    "PossessivePronoun": 0,
    "PriceLow": 2,
    "PriceMid": 3075,
    "Pronoun": 0,
    "Rarity": 1,
    "Recipes": [
        {
            "ClassJobID": 11,
            "ID": 3838,
            "Level": 71
        }
    ],
    "RequiredPvpRank": 0,
    "Singular": "hard mudstone whetstone",
    "Singular_de": "Mergelwetzstein",
    "Singular_en": "hard mudstone whetstone",
    "Singular_fr": "pierre \u00e0 aiguiser en mudstone solide",
    "Singular_ja": "\u786c\u6ce5\u5ca9\u7825\u77f3",
    "StackSize": 999,
    "StartsWithVowel": 0,
    "SubStatCategory": 0,
    "Url": "/Item/27802"
}